tree_collection.cpython-313-darwin.so
tests/__init__.py
tests/test.py
tests/data/class1_5.phy
tests/data/class1_4.phy
tests/data/class3_4.phy
tests/data/class3_5.phy
tests/data/class3_1.phy
tests/data/class1_3.phy
tests/data/class1_2.phy
tests/data/class3_2.phy
tests/data/class1_1.phy
tests/data/class3_3.phy
tests/data/class2_4.phy
tests/data/class2_5.phy
tests/data/class2_2.phy
tests/data/class2_3.phy
tests/data/class2_1.phy
tests/data/trees/class2_2.nwk
tests/data/trees/class2_3.nwk
tests/data/trees/class2_1.nwk
tests/data/trees/class2_4.nwk
tests/data/trees/class2_5.nwk
tests/data/trees/class3_1.nwk
tests/data/trees/class1_3.nwk
tests/data/trees/class1_2.nwk
tests/data/trees/class3_2.nwk
tests/data/trees/class1_1.nwk
tests/data/trees/class3_3.nwk
tests/data/trees/class1_5.nwk
tests/data/trees/class1_4.nwk
tests/data/trees/class3_4.nwk
tests/data/trees/class3_5.nwk
tests/data/cache/class3_1.json.gz
tests/data/cache/class2_2.json.gz
tests/data/cache/class2_3.json.gz
tests/data/cache/class2_1.json.gz
tests/data/cache/class1_5.json.gz
tests/data/cache/geo_dm.csv
tests/data/cache/class3_2.json.gz
tests/data/cache/class3_3.json.gz
tests/data/cache/class1_4.json.gz
tests/data/cache/class2_5.json.gz
tests/data/cache/class1_1.json.gz
tests/data/cache/class2_4.json.gz
tests/data/cache/class3_5.json.gz
tests/data/cache/class1_2.json.gz
tests/data/cache/class1_3.json.gz
tests/data/cache/class3_4.json.gz
tests/data/mini/class1_1.phy
tests/data/mini/class1_1.phy.bz2
tests/data/mini/class1_1.phy.gz
tests/data/mini/class1_1.fas.bz2
tests/data/mini/class1_1.fas
tests/data/mini/class1_1.fas.gz
tests/data/dna_alignments/class0_0_dna.phy
tests/data/parsing/RAxML_bestTree.aamulti
tests/data/parsing/RAxML_info.aamulti
tests/data/parsing/RAxML_result.modoptq
tests/data/parsing/RAxML_info.dnamulti
tests/data/parsing/RAxML_info.modopt
tests/data/parsing/RAxML_result.modopt
tests/data/parsing/RAxML_info.modoptq
treeCl-0.1.41.dist-info/RECORD
treeCl-0.1.41.dist-info/WHEEL
treeCl-0.1.41.dist-info/top_level.txt
treeCl-0.1.41.dist-info/LICENSE.txt
treeCl-0.1.41.dist-info/METADATA
