Metadata-Version: 2.1
Name: treeCl
Version: 0.1.41
Summary: Phylogenetic Clustering Package
Home-page: https://github.com/kgori/treeCl.git
Author: Kevin Gori
Author-email: kcg25@cam.ac.uk
License-File: LICENSE.txt
Requires-Dist: biopython
Requires-Dist: cython>=0.19.0
Requires-Dist: dendropy>=4.0.0
Requires-Dist: fastcluster
Requires-Dist: futures; python_version == "2.7"
Requires-Dist: ipython
Requires-Dist: matplotlib
Requires-Dist: nose
Requires-Dist: numpy
Requires-Dist: pandas
Requires-Dist: phylo_utils==0.0.10
Requires-Dist: progressbar-latest==2.4
Requires-Dist: PyYaml
Requires-Dist: scipy
Requires-Dist: scikit-learn
Requires-Dist: tree_distance>=1.0.12
